{
  "neutral": {
    "metaphors": [
      "comme une onde qui se propage",
      "tel un miroir qui reflète l'essence",
      "semblable à une graine qui germe",
      "comme un écho qui se multiplie",
      "tel un réseau de connexions",
      "semblable à une symphonie en construction",
      "comme une lumière qui illumine",
      "tel un pont entre les mondes",
      "semblable à un cristal qui se forme",
      "comme un voyage intérieur",
      "tel un cœur qui pulse",
      "semblable à une spirale infinie"
    ],
    "openQuestions": [
      "Que porte ce mot pour vous?",
      "Où ce concept vous mène-t-il?",
      "Quelle résonnance cela crée-t-il en vous?",
      "Comment ce sens se déploie-t-il?",
      "Quel écho cherchez-vous à entendre?",
      "Qu'est-ce que cela signifie vraiment pour vous?",
      "Où réside la vérité de ce que vous dites?",
      "Comment ces mots se nouent-ils ensemble?",
      "Quel chemin suit cette pensée?",
      "Qu'y a-t-il au cœur de votre intention?",
      "Comment ce message vous transforme-t-il?",
      "Quel sens latent attendait d'être découvert?"
    ],
    "sentenceStructures": [
      "Le cœur de votre message: {pivot}. Cela résonne avec: {cowords}.",
      "{pivot}... ce mot porte votre intention. Autour: {cowords}.",
      "Vous avez dit {pivot}. L'écho reflète: {cowords}.",
      "Votre parole centrale: {pivot}. Elle vibre entre: {cowords}.",
      "Au fondement de vos mots: {pivot}. Ils dialoguent avec: {cowords}.",
      "{pivot} émerge. Accompagné de: {cowords}.",
      "Essence identifiée: {pivot}. Ses résonances: {cowords}.",
      "Le noyau: {pivot}. La danse autour: {cowords}."
    ]
  },
  "hypno": {
    "metaphors": [
      "comme un souffle qui cherche son rythme",
      "comme une vague discrète qui revient sans bruit",
      "comme un sentier que l'on devine plus qu'on ne voit",
      "comme une clé posée sur une table inconnue",
      "comme une porte entrouverte dans un couloir silencieux",
      "comme un courant d'air qui porte une odeur ancienne",
      "comme un fil qui attend qu'on le touche",
      "comme une étoile isolée dans un ciel sans nuage",
      "comme une graine qui ignore encore sa forme",
      "comme un miroir voilé de buée",
      "comme une chambre sans lumière où l'on retrouve ses pas",
      "comme un secret roulé dans un coquillage",
      "comme un papier plié trop longtemps",
      "comme un nom écrit au crayon",
      "comme une plume retenue dans l'air",
      "comme une présence derrière le rideau",
      "comme un ruisseau qui parle bas",
      "comme une note suspendue au-dessus du silence",
      "comme la trace d'une eau ancienne sur la pierre",
      "comme un parfum qui revient sans souvenir",
      "comme un objet trouvé sans histoire",
      "comme une fenêtre donnant sur l'invisible",
      "comme un escalier qui ne dit pas où il mène",
      "comme une lumière aperçue du coin de l'œil"
    ],
    "openQuestions": [
      "Que deviendrait cette sensation si on lui offrait un instant de repos ?",
      "Comment se déploierait-elle si tu la laissais respirer davantage ?",
      "Si cette image se précisait, quelle couleur prendrait-elle ?",
      "Qu’est-ce qui changerait si tu restais à proximité, sans agir ?",
      "Si ce mot pouvait se poser quelque part, où serait-ce ?",
      "Quel rythme adopterait-il si c’était une vague ?",
      "Que se passerait-il si tu ne le retenais pas ?",
      "Quelle forme prend-il quand tu le laisses venir ?",
      "Et si tu le regardais sans y répondre ?",
      "Quel espace cela crée en toi quand tu l’observes ?",
      "De quoi aurait-il besoin pour te parler plus doucement ?",
      "Se protège-t-il ou protège-t-il quelque chose ?",
      "Que dit-il quand tu n’essaies plus de comprendre ?",
      "Quelle distance te conviendrait pour le rencontrer ?",
      "Si tu pouvais t’y appuyer, que sentirais-tu ?",
      "Et si tu en faisais un guide provisoire ?",
      "Que se passe-t-il juste avant qu’il n’apparaisse ?",
      "Et juste après qu’il passe ?",
      "Comment bouge ton souffle lorsque tu y penses ?",
      "Et si tu lui donnais un autre tempo ?",
      "Que devient-il si tu le laisses flotter un peu plus loin ?",
      "Que raconte le silence autour ?",
      "S’il avait une direction, laquelle indiquerait-il ?",
      "Quelle forme prend la suite, si tu n’accélères pas ?"
    ],
    "sentenceStructures": [
      "« {pivot} » apparaît {meta}. Entre « {noyau} » et « {peripherie} », quelque chose semble vouloir se dire. {question}",
      "Dans ce que tu évoques, « {pivot} » se présente {meta}. Il touche à la fois « {noyau} » et « {peripherie} ». Si tu restes proche de cette image un moment : {question}",
      "« {pivot} » traverse ton message {meta}. Il fait résonner « {noyau} » et « {peripherie} » comme deux échos. Sans chercher à comprendre : {question}"
    ]
  },
  "ado": {
    "metaphors": [
      "style un truc de fou qui buzz",
      "genre une bombe qui explose",
      "c'est grave comme une déflagration",
      "c'est dingue comme une tornade",
      "ça clash trop fort avec les autres",
      "style une grosse vague qui débarque",
      "c'est chaud comme du feu liquide",
      "grave une créature sauvage",
      "c'est ouf comme un chaos organisé",
      "genre trop puissant pour exister",
      "c'est sick comme du poison vivant",
      "style un tremblement de terre psychique"
    ],
    "openQuestions": [
      "T'as vraiment senti ce truc?",
      "C'est fou pas?",
      "T'en penses quoi franchement?",
      "Ça t'a choc ou quoi?",
      "Pourquoi ça te parle autant?",
      "T'as compris ou c'est trop hard?",
      "Ça te rend dingue pas?",
      "C'est ce que tu cherchais?",
      "T'as vu comment ça clash?",
      "Pourquoi c'est comme ça?",
      "Ça te change du quotidien hein?",
      "T'es ouf de ça ou pas?"
    ],
    "sentenceStructures": [
      "Yo {pivot} c'est DEL! Avec {cowords} c'est trop.",
      "{pivot} boom! Attaché à {cowords} trop fort.",
      "Ce truc {pivot}... c'est fou avec {cowords}...",
      "Grave {pivot} c'est énorme, {cowords} partout.",
      "{pivot} clash trop hard avec {cowords}.",
      "Le core: {pivot}. Autour: {cowords} qui tue.",
      "Incroyable {pivot}! Mélangé avec {cowords} c'est ouf.",
      "{pivot} pète avec {cowords}! Trop hype!"
    ]
  },
  "etp": {
    "metaphors": [
      "comme une graine qui grandit dans le jardin du cœur",
      "tel un enfant qui apprend à marcher",
      "semblable à un papillon qui sort de son cocon",
      "comme une fleur qui s'ouvre au soleil",
      "tel un arbre qui développe ses racines",
      "semblable à une histoire qui se compose page à page",
      "comme un jeu où on apprend ensemble",
      "tel un pont de couleurs arc-en-ciel",
      "semblable à un trésor qu'on découvre pas à pas",
      "comme un ami fidèle qui t'accompagne",
      "tel un chemin illuminé et sécuritaire",
      "semblable à un rêve positif qui devient réalité"
    ],
    "openQuestions": [
      "Qu'as-tu appris de ce mot?",
      "Comment ce mot t'aide-t-il à grandir?",
      "Que ressentais-tu en le disant?",
      "Quel trésor ce mot cache-t-il?",
      "Comment partagerais-tu cela avec d'autres?",
      "Qu'aimes-tu le plus dans ce mot?",
      "Comment ce mot te rend-il plus fort?",
      "Quel ami reconnaissais-tu dans ce mot?",
      "Comment ce mot illumine-t-il ta journée?",
      "Qu'aimais-tu faire avec ce concept?",
      "Comment ce mot te donne-t-il de l'espoir?",
      "Quel cadeau ce mot t'a-t-il offert?"
    ],
    "sentenceStructures": [
      "Le cœur: {pivot}. Et autour: {cowords} qui grandissent.",
      "{pivot}... c'est joli avec {cowords}... ensemble.",
      "Tu as dit {pivot}. Bravo! {cowords} te soutiennent.",
      "Super {pivot}! {cowords} t'accompagnent.",
      "Le merveilleux {pivot}. Entouré de {cowords} aimants.",
      "Excellent {pivot}! {cowords} dansent autour.",
      "{pivot} brille. {cowords} brillent aussi. Magnifique!",
      "Ton {{pivot}} est une fleur. {{cowords}} fleurissent près!"
    ]
  }
}

